{
    "data": [
        {
            "gameRecord": "",
            "addTime": "2023-12-12 17:40:46",
            "countdownSeconds": 30,
            "gameNo": "174046"
        },
        {
            "gameRecord": "2$2",
            "addTime": "2023-12-12 17:40:42",
            "countdownSeconds": 30,
            "gameNo": "174042"
        },
        {
            "gameRecord": "1$1",
            "addTime": "2023-12-12 17:40:38",
            "countdownSeconds": 30,
            "gameNo": "174038"
        },
        {
            "gameRecord": "1$1",
            "addTime": "2023-12-12 17:40:34",
            "countdownSeconds": 30,
            "gameNo": "174034"
        },
        {
            "gameRecord": "2$3",
            "addTime": "2023-12-12 17:40:30",
            "countdownSeconds": 30,
            "gameNo": "174030"
        },
        {
            "gameRecord": "3$0",
            "addTime": "2023-12-12 17:40:26",
            "countdownSeconds": 30,
            "gameNo": "174026"
        },
        {
            "gameRecord": "1$1",
            "addTime": "2023-12-12 17:40:22",
            "countdownSeconds": 30,
            "gameNo": "174022"
        },
        {
            "gameRecord": "2$3",
            "addTime": "2023-12-12 17:40:18",
            "countdownSeconds": 30,
            "gameNo": "174018"
        },
        {
            "gameRecord": "3$3",
            "addTime": "2023-12-12 17:40:14",
            "countdownSeconds": 30,
            "gameNo": "174014"
        },
        {
            "gameRecord": "3$2",
            "addTime": "2023-12-12 17:40:10",
            "countdownSeconds": 30,
            "gameNo": "174010"
        },
        {
            "gameRecord": "1$2",
            "addTime": "2023-12-12 17:40:06",
            "countdownSeconds": 30,
            "gameNo": "174006"
        },
        {
            "gameRecord": "1$3",
            "addTime": "2023-12-12 17:40:02",
            "countdownSeconds": 30,
            "gameNo": "174002"
        },
        {
            "gameRecord": "2$2",
            "addTime": "2023-12-12 17:39:58",
            "countdownSeconds": 30,
            "gameNo": "173958"
        },
        {
            "gameRecord": "3$0",
            "addTime": "2023-12-12 17:39:54",
            "countdownSeconds": 30,
            "gameNo": "173954"
        },
        {
            "gameRecord": "1$0",
            "addTime": "2023-12-12 17:39:50",
            "countdownSeconds": 30,
            "gameNo": "173950"
        },
        {
            "gameRecord": "2$1",
            "addTime": "2023-12-12 17:39:46",
            "countdownSeconds": 30,
            "gameNo": "173946"
        },
        {
            "gameRecord": "3$3",
            "addTime": "2023-12-12 17:39:42",
            "countdownSeconds": 30,
            "gameNo": "173942"
        },
        {
            "gameRecord": "3$1",
            "addTime": "2023-12-12 17:39:38",
            "countdownSeconds": 30,
            "gameNo": "173938"
        },
        {
            "gameRecord": "2$3",
            "addTime": "2023-12-12 17:39:34",
            "countdownSeconds": 30,
            "gameNo": "173934"
        },
        {
            "gameRecord": "1$2",
            "addTime": "2023-12-12 17:39:30",
            "countdownSeconds": 30,
            "gameNo": "173930"
        },
        {
            "gameRecord": "3$1",
            "addTime": "2023-12-12 17:39:26",
            "countdownSeconds": 30,
            "gameNo": "173926"
        },
        {
            "gameRecord": "1$2",
            "addTime": "2023-12-12 17:39:22",
            "countdownSeconds": 30,
            "gameNo": "173922"
        },
        {
            "gameRecord": "1$2",
            "addTime": "2023-12-12 17:39:18",
            "countdownSeconds": 30,
            "gameNo": "173918"
        },
        {
            "gameRecord": "3$0",
            "addTime": "2023-12-12 17:39:14",
            "countdownSeconds": 30,
            "gameNo": "173914"
        },
        {
            "gameRecord": "2$0",
            "addTime": "2023-12-12 17:39:10",
            "countdownSeconds": 30,
            "gameNo": "173910"
        },
        {
            "gameRecord": "3$0",
            "addTime": "2023-12-12 17:39:06",
            "countdownSeconds": 30,
            "gameNo": "173906"
        },
        {
            "gameRecord": "1$3",
            "addTime": "2023-12-12 17:39:02",
            "countdownSeconds": 30,
            "gameNo": "173902"
        },
        {
            "gameRecord": "3$3",
            "addTime": "2023-12-12 17:38:58",
            "countdownSeconds": 30,
            "gameNo": "173858"
        },
        {
            "gameRecord": "1$3",
            "addTime": "2023-12-12 17:38:54",
            "countdownSeconds": 30,
            "gameNo": "173854"
        },
        {
            "gameRecord": "2$3",
            "addTime": "2023-12-12 17:38:50",
            "countdownSeconds": 30,
            "gameNo": "173850"
        },
        {
            "gameRecord": "3$0",
            "addTime": "2023-12-12 17:38:46",
            "countdownSeconds": 30,
            "gameNo": "173846"
        },
        {
            "gameRecord": "1$3",
            "addTime": "2023-12-12 17:38:42",
            "countdownSeconds": 30,
            "gameNo": "173842"
        },
        {
            "gameRecord": "1$0",
            "addTime": "2023-12-12 17:38:38",
            "countdownSeconds": 30,
            "gameNo": "173838"
        },
        {
            "gameRecord": "3$3",
            "addTime": "2023-12-12 17:38:34",
            "countdownSeconds": 30,
            "gameNo": "173834"
        },
        {
            "gameRecord": "3$3",
            "addTime": "2023-12-12 17:38:30",
            "countdownSeconds": 30,
            "gameNo": "173830"
        },
        {
            "gameRecord": "1$2",
            "addTime": "2023-12-12 17:38:26",
            "countdownSeconds": 30,
            "gameNo": "173826"
        },
        {
            "gameRecord": "1$0",
            "addTime": "2023-12-12 17:38:22",
            "countdownSeconds": 30,
            "gameNo": "173822"
        },
        {
            "gameRecord": "3$0",
            "addTime": "2023-12-12 17:38:18",
            "countdownSeconds": 30,
            "gameNo": "173818"
        },
        {
            "gameRecord": "2$1",
            "addTime": "2023-12-12 17:38:14",
            "countdownSeconds": 30,
            "gameNo": "173814"
        },
        {
            "gameRecord": "2$3",
            "addTime": "2023-12-12 17:38:10",
            "countdownSeconds": 30,
            "gameNo": "173810"
        },
        {
            "gameRecord": "2$1",
            "addTime": "2023-12-12 17:38:06",
            "countdownSeconds": 30,
            "gameNo": "173806"
        },
        {
            "gameRecord": "3$0",
            "addTime": "2023-12-12 17:38:02",
            "countdownSeconds": 30,
            "gameNo": "173802"
        },
        {
            "gameRecord": "2$2",
            "addTime": "2023-12-12 17:37:58",
            "countdownSeconds": 30,
            "gameNo": "173758"
        },
        {
            "gameRecord": "1$0",
            "addTime": "2023-12-12 17:37:54",
            "countdownSeconds": 30,
            "gameNo": "173754"
        },
        {
            "gameRecord": "2$2",
            "addTime": "2023-12-12 17:37:50",
            "countdownSeconds": 30,
            "gameNo": "173750"
        },
        {
            "gameRecord": "3$2",
            "addTime": "2023-12-12 17:37:46",
            "countdownSeconds": 30,
            "gameNo": "173746"
        },
        {
            "gameRecord": "1$3",
            "addTime": "2023-12-12 17:37:42",
            "countdownSeconds": 30,
            "gameNo": "173742"
        },
        {
            "gameRecord": "2$3",
            "addTime": "2023-12-12 17:37:38",
            "countdownSeconds": 30,
            "gameNo": "173738"
        },
        {
            "gameRecord": "2$1",
            "addTime": "2023-12-12 17:37:34",
            "countdownSeconds": 30,
            "gameNo": "173734"
        },
        {
            "gameRecord": "2$3",
            "addTime": "2023-12-12 17:37:30",
            "countdownSeconds": 30,
            "gameNo": "173730"
        },
        {
            "gameRecord": "3$3",
            "addTime": "2023-12-12 17:37:26",
            "countdownSeconds": 30,
            "gameNo": "173726"
        },
        {
            "gameRecord": "3$3",
            "addTime": "2023-12-12 17:37:22",
            "countdownSeconds": 30,
            "gameNo": "173722"
        },
        {
            "gameRecord": "1$1",
            "addTime": "2023-12-12 17:37:18",
            "countdownSeconds": 30,
            "gameNo": "173718"
        },
        {
            "gameRecord": "3$0",
            "addTime": "2023-12-12 17:37:14",
            "countdownSeconds": 30,
            "gameNo": "173714"
        },
        {
            "gameRecord": "1$3",
            "addTime": "2023-12-12 17:37:10",
            "countdownSeconds": 30,
            "gameNo": "173710"
        },
        {
            "gameRecord": "1$2",
            "addTime": "2023-12-12 17:37:06",
            "countdownSeconds": 30,
            "gameNo": "173706"
        },
        {
            "gameRecord": "1$3",
            "addTime": "2023-12-12 17:37:02",
            "countdownSeconds": 30,
            "gameNo": "173702"
        },
        {
            "gameRecord": "2$2",
            "addTime": "2023-12-12 17:36:58",
            "countdownSeconds": 30,
            "gameNo": "173658"
        },
        {
            "gameRecord": "1$0",
            "addTime": "2023-12-12 17:36:54",
            "countdownSeconds": 30,
            "gameNo": "173654"
        },
        {
            "gameRecord": "3$0",
            "addTime": "2023-12-12 17:36:50",
            "countdownSeconds": 30,
            "gameNo": "173650"
        },
        {
            "gameRecord": "1$1",
            "addTime": "2023-12-12 17:36:46",
            "countdownSeconds": 30,
            "gameNo": "173646"
        },
        {
            "gameRecord": "3$2",
            "addTime": "2023-12-12 17:36:42",
            "countdownSeconds": 30,
            "gameNo": "173642"
        },
        {
            "gameRecord": "2$2",
            "addTime": "2023-12-12 17:36:38",
            "countdownSeconds": 30,
            "gameNo": "173638"
        },
        {
            "gameRecord": "1$2",
            "addTime": "2023-12-12 17:36:34",
            "countdownSeconds": 30,
            "gameNo": "173634"
        },
        {
            "gameRecord": "2$1",
            "addTime": "2023-12-12 17:36:30",
            "countdownSeconds": 30,
            "gameNo": "173630"
        },
        {
            "gameRecord": "1$0",
            "addTime": "2023-12-12 17:36:26",
            "countdownSeconds": 30,
            "gameNo": "173626"
        },
        {
            "gameRecord": "3$0",
            "addTime": "2023-12-12 17:36:22",
            "countdownSeconds": 30,
            "gameNo": "173622"
        },
        {
            "gameRecord": "2$1",
            "addTime": "2023-12-12 17:36:18",
            "countdownSeconds": 30,
            "gameNo": "173618"
        },
        {
            "gameRecord": "2$3",
            "addTime": "2023-12-12 17:36:14",
            "countdownSeconds": 30,
            "gameNo": "173614"
        },
        {
            "gameRecord": "3$0",
            "addTime": "2023-12-12 17:36:10",
            "countdownSeconds": 30,
            "gameNo": "173610"
        },
        {
            "gameRecord": "2$2",
            "addTime": "2023-12-12 17:36:06",
            "countdownSeconds": 30,
            "gameNo": "173606"
        },
        {
            "gameRecord": "3$1",
            "addTime": "2023-12-12 17:36:02",
            "countdownSeconds": 30,
            "gameNo": "173602"
        },
        {
            "gameRecord": "2$0",
            "addTime": "2023-12-12 17:35:58",
            "countdownSeconds": 30,
            "gameNo": "173558"
        },
        {
            "gameRecord": "3$1",
            "addTime": "2023-12-12 17:35:54",
            "countdownSeconds": 30,
            "gameNo": "173554"
        },
        {
            "gameRecord": "2$2",
            "addTime": "2023-12-12 17:35:49",
            "countdownSeconds": 30,
            "gameNo": "173549"
        },
        {
            "gameRecord": "2$1",
            "addTime": "2023-12-12 17:35:45",
            "countdownSeconds": 30,
            "gameNo": "173545"
        },
        {
            "gameRecord": "1$0",
            "addTime": "2023-12-12 17:35:41",
            "countdownSeconds": 30,
            "gameNo": "173541"
        },
        {
            "gameRecord": "2$0",
            "addTime": "2023-12-12 17:35:37",
            "countdownSeconds": 30,
            "gameNo": "173537"
        },
        {
            "gameRecord": "1$2",
            "addTime": "2023-12-12 17:35:33",
            "countdownSeconds": 30,
            "gameNo": "173533"
        },
        {
            "gameRecord": "1$0",
            "addTime": "2023-12-12 17:35:29",
            "countdownSeconds": 30,
            "gameNo": "173529"
        },
        {
            "gameRecord": "3$3",
            "addTime": "2023-12-12 17:35:25",
            "countdownSeconds": 30,
            "gameNo": "173525"
        },
        {
            "gameRecord": "3$0",
            "addTime": "2023-12-12 17:35:21",
            "countdownSeconds": 30,
            "gameNo": "173521"
        },
        {
            "gameRecord": "2$1",
            "addTime": "2023-12-12 17:35:17",
            "countdownSeconds": 30,
            "gameNo": "173517"
        },
        {
            "gameRecord": "2$1",
            "addTime": "2023-12-12 17:35:13",
            "countdownSeconds": 30,
            "gameNo": "173513"
        },
        {
            "gameRecord": "1$2",
            "addTime": "2023-12-12 17:35:09",
            "countdownSeconds": 30,
            "gameNo": "173509"
        },
        {
            "gameRecord": "3$2",
            "addTime": "2023-12-12 17:35:05",
            "countdownSeconds": 30,
            "gameNo": "173505"
        },
        {
            "gameRecord": "1$3",
            "addTime": "2023-12-12 17:35:01",
            "countdownSeconds": 30,
            "gameNo": "173501"
        },
        {
            "gameRecord": "1$1",
            "addTime": "2023-12-12 17:34:57",
            "countdownSeconds": 30,
            "gameNo": "173457"
        },
        {
            "gameRecord": "2$1",
            "addTime": "2023-12-12 17:34:53",
            "countdownSeconds": 30,
            "gameNo": "173453"
        },
        {
            "gameRecord": "2$3",
            "addTime": "2023-12-12 17:34:49",
            "countdownSeconds": 30,
            "gameNo": "173449"
        },
        {
            "gameRecord": "3$1",
            "addTime": "2023-12-12 17:34:45",
            "countdownSeconds": 30,
            "gameNo": "173445"
        },
        {
            "gameRecord": "3$3",
            "addTime": "2023-12-12 17:34:41",
            "countdownSeconds": 30,
            "gameNo": "173441"
        },
        {
            "gameRecord": "2$1",
            "addTime": "2023-12-12 17:34:37",
            "countdownSeconds": 30,
            "gameNo": "173437"
        },
        {
            "gameRecord": "2$3",
            "addTime": "2023-12-12 17:34:33",
            "countdownSeconds": 30,
            "gameNo": "173433"
        },
        {
            "gameRecord": "2$3",
            "addTime": "2023-12-12 17:34:29",
            "countdownSeconds": 30,
            "gameNo": "173429"
        },
        {
            "gameRecord": "2$3",
            "addTime": "2023-12-12 17:34:25",
            "countdownSeconds": 30,
            "gameNo": "173425"
        },
        {
            "gameRecord": "1$0",
            "addTime": "2023-12-12 17:34:21",
            "countdownSeconds": 30,
            "gameNo": "173421"
        },
        {
            "gameRecord": "1$2",
            "addTime": "2023-12-12 17:34:17",
            "countdownSeconds": 30,
            "gameNo": "173417"
        },
        {
            "gameRecord": "2$1",
            "addTime": "2023-12-12 17:34:13",
            "countdownSeconds": 30,
            "gameNo": "173413"
        },
        {
            "gameRecord": "2$0",
            "addTime": "2023-12-12 17:34:09",
            "countdownSeconds": 30,
            "gameNo": "173409"
        },
        {
            "gameRecord": "2$0",
            "addTime": "2023-12-12 17:34:05",
            "countdownSeconds": 30,
            "gameNo": "173405"
        }
    ]
}